pyalp/__init__.py
pyalp-0.0.1.dist-info/METADATA
pyalp-0.0.1.dist-info/WHEEL
pyalp-0.0.1.dist-info/top_level.txt
pyalp-0.0.1.dist-info/RECORD
